{
    "0": {
        "Name": "Mitch Mooney",
        "Strokes": "291",
        "Purse": "616",
        "Time (ET)": "-",
        "3": "76",
        "2": "71",
        "4": "74",
        "player_id": "5572"
    },
    "1": {
        "Name": "Mike Peck",
        "Strokes": "290",
        "Purse": "627",
        "Time (ET)": "-",
        "3": "74",
        "2": "73",
        "4": "74",
        "player_id": "5370"
    },
    "2": {
        "Name": "George Cadle",
        "Strokes": "290",
        "Purse": "627",
        "Time (ET)": "-",
        "3": "74",
        "2": "71",
        "4": "75",
        "player_id": "5162"
    },
    "3": {
        "Name": "Gene Littler",
        "Strokes": "288",
        "Purse": "644",
        "Time (ET)": "-",
        "3": "78",
        "2": "70",
        "4": "68",
        "player_id": "855"
    },
    "4": {
        "Name": "Joe Inman",
        "Strokes": "288",
        "Purse": "644",
        "Time (ET)": "-",
        "3": "72",
        "2": "70",
        "4": "75",
        "player_id": "337"
    },
    "5": {
        "Name": "Scott Bess",
        "Strokes": "288",
        "Purse": "644",
        "Time (ET)": "-",
        "3": "74",
        "2": "72",
        "4": "72",
        "player_id": "3547"
    },
    "6": {
        "Name": "Kenny Knox",
        "Strokes": "287",
        "Purse": "665",
        "Time (ET)": "-",
        "3": "73",
        "2": "70",
        "4": "72",
        "player_id": "454"
    },
    "7": {
        "Name": "Bill Galloway",
        "Strokes": "287",
        "Purse": "665",
        "Time (ET)": "-",
        "3": "72",
        "2": "70",
        "4": "74",
        "player_id": "5575"
    },
    "8": {
        "Name": "Stanton Altgelt",
        "Strokes": "287",
        "Purse": "665",
        "Time (ET)": "-",
        "3": "73",
        "2": "71",
        "4": "74",
        "player_id": "5475"
    },
    "9": {
        "Name": "Jack Renner",
        "Strokes": "286",
        "Purse": "683",
        "Time (ET)": "-",
        "3": "73",
        "2": "71",
        "4": "72",
        "player_id": "620"
    },
    "10": {
        "Name": "Jim Dent",
        "Strokes": "286",
        "Purse": "683",
        "Time (ET)": "-",
        "3": "77",
        "2": "71",
        "4": "69",
        "player_id": "787"
    },
    "11": {
        "Name": "Dave Stockton Sr.",
        "Strokes": "285",
        "Purse": "700",
        "Time (ET)": "-",
        "3": "70",
        "2": "70",
        "4": "74",
        "player_id": "773"
    },
    "12": {
        "Name": "Ben Crenshaw",
        "Strokes": "285",
        "Purse": "700",
        "Time (ET)": "-",
        "3": "70",
        "2": "72",
        "4": "73",
        "player_id": "24"
    },
    "13": {
        "Name": "Bobby Cole",
        "Strokes": "285",
        "Purse": "700",
        "Time (ET)": "-",
        "3": "75",
        "2": "65",
        "4": "71",
        "player_id": "1035"
    },
    "14": {
        "Name": "Pat McGowan",
        "Strokes": "284",
        "Purse": "721",
        "Time (ET)": "-",
        "3": "72",
        "2": "70",
        "4": "71",
        "player_id": "4180"
    },
    "15": {
        "Name": "Fred Marti",
        "Strokes": "284",
        "Purse": "721",
        "Time (ET)": "-",
        "3": "71",
        "2": "70",
        "4": "71",
        "player_id": "5454"
    },
    "16": {
        "Name": "Bruce Douglass",
        "Strokes": "284",
        "Purse": "721",
        "Time (ET)": "-",
        "3": "68",
        "2": "72",
        "4": "74",
        "player_id": "5400"
    },
    "17": {
        "Name": "Tom Storey",
        "Strokes": "283",
        "Purse": "749",
        "Time (ET)": "-",
        "3": "72",
        "2": "70",
        "4": "70",
        "player_id": "951"
    },
    "18": {
        "Name": "Bob Payne",
        "Strokes": "283",
        "Purse": "749",
        "Time (ET)": "-",
        "3": "69",
        "2": "72",
        "4": "72",
        "player_id": "5578"
    },
    "19": {
        "Name": "Wayne Levi",
        "Strokes": "283",
        "Purse": "749",
        "Time (ET)": "-",
        "3": "71",
        "2": "68",
        "4": "73",
        "player_id": "187"
    },
    "20": {
        "Name": "Billy Kratzert",
        "Strokes": "283",
        "Purse": "749",
        "Time (ET)": "-",
        "3": "69",
        "2": "73",
        "4": "72",
        "player_id": "2002"
    },
    "21": {
        "Name": "Terry Diehl",
        "Strokes": "283",
        "Purse": "749",
        "Time (ET)": "-",
        "3": "71",
        "2": "68",
        "4": "72",
        "player_id": "5176"
    },
    "22": {
        "Name": "Lance Ten Broeck",
        "Strokes": "282",
        "Purse": "784",
        "Time (ET)": "-",
        "3": "72",
        "2": "67",
        "4": "70",
        "player_id": "642"
    },
    "23": {
        "Name": "Bob Shearer",
        "Strokes": "282",
        "Purse": "784",
        "Time (ET)": "-",
        "3": "75",
        "2": "71",
        "4": "68",
        "player_id": "1828"
    },
    "24": {
        "Name": "Gil Morgan",
        "Strokes": "282",
        "Purse": "784",
        "Time (ET)": "-",
        "3": "78",
        "2": "72",
        "4": "67",
        "player_id": "74"
    },
    "25": {
        "Name": "Lee Elder",
        "Strokes": "282",
        "Purse": "784",
        "Time (ET)": "-",
        "3": "70",
        "2": "72",
        "4": "71",
        "player_id": "849"
    },
    "26": {
        "Name": "Michael Brannan",
        "Strokes": "282",
        "Purse": "784",
        "Time (ET)": "-",
        "3": "73",
        "2": "73",
        "4": "68",
        "player_id": "5455"
    },
    "27": {
        "Name": "Mike Hill",
        "Strokes": "281",
        "Purse": "829",
        "Time (ET)": "-",
        "3": "72",
        "2": "69",
        "4": "68",
        "player_id": "781"
    },
    "28": {
        "Name": "Mark Hayes",
        "Strokes": "281",
        "Purse": "829",
        "Time (ET)": "-",
        "3": "73",
        "2": "73",
        "4": "66",
        "player_id": "421"
    },
    "29": {
        "Name": "Charles Coody",
        "Strokes": "281",
        "Purse": "829",
        "Time (ET)": "-",
        "3": "73",
        "2": "68",
        "4": "69",
        "player_id": "312"
    },
    "30": {
        "Name": "Butch Baird",
        "Strokes": "281",
        "Purse": "829",
        "Time (ET)": "-",
        "3": "74",
        "2": "68",
        "4": "70",
        "player_id": "823"
    },
    "31": {
        "Name": "George Archer",
        "Strokes": "281",
        "Purse": "829",
        "Time (ET)": "-",
        "3": "73",
        "2": "68",
        "4": "71",
        "player_id": "800"
    },
    "32": {
        "Name": "Leonard Thompson",
        "Strokes": "280",
        "Purse": "1201",
        "Time (ET)": "-",
        "3": "75",
        "2": "67",
        "4": "65",
        "player_id": "803"
    },
    "33": {
        "Name": "J.C. Snead",
        "Strokes": "280",
        "Purse": "1201",
        "Time (ET)": "-",
        "3": "68",
        "2": "73",
        "4": "71",
        "player_id": "795"
    },
    "34": {
        "Name": "Andy North",
        "Strokes": "280",
        "Purse": "1201",
        "Time (ET)": "-",
        "3": "68",
        "2": "68",
        "4": "71",
        "player_id": "606"
    },
    "35": {
        "Name": "Jim Nelford",
        "Strokes": "280",
        "Purse": "1201",
        "Time (ET)": "-",
        "3": "70",
        "2": "73",
        "4": "70",
        "player_id": "1099"
    },
    "36": {
        "Name": "Bob Murphy",
        "Strokes": "280",
        "Purse": "1201",
        "Time (ET)": "-",
        "3": "72",
        "2": "71",
        "4": "67",
        "player_id": "783"
    },
    "37": {
        "Name": "John Mazza",
        "Strokes": "280",
        "Purse": "1201",
        "Time (ET)": "-",
        "3": "73",
        "2": "71",
        "4": "67",
        "player_id": "398"
    },
    "38": {
        "Name": "Peter Jacobsen",
        "Strokes": "280",
        "Purse": "1201",
        "Time (ET)": "-",
        "3": "73",
        "2": "67",
        "4": "65",
        "player_id": "8"
    },
    "39": {
        "Name": "Bunky Henry",
        "Strokes": "280",
        "Purse": "1201",
        "Time (ET)": "-",
        "3": "71",
        "2": "71",
        "4": "70",
        "player_id": "837"
    },
    "40": {
        "Name": "Morris Hatalsky",
        "Strokes": "280",
        "Purse": "1201",
        "Time (ET)": "-",
        "3": "69",
        "2": "72",
        "4": "71",
        "player_id": "1740"
    },
    "41": {
        "Name": "Danny Edwards",
        "Strokes": "280",
        "Purse": "1201",
        "Time (ET)": "-",
        "3": "68",
        "2": "72",
        "4": "73",
        "player_id": "335"
    },
    "42": {
        "Name": "Dale Douglass",
        "Strokes": "280",
        "Purse": "1201",
        "Time (ET)": "-",
        "3": "67",
        "2": "70",
        "4": "71",
        "player_id": "806"
    },
    "43": {
        "Name": "Wally Armstrong",
        "Strokes": "280",
        "Purse": "1201",
        "Time (ET)": "-",
        "3": "72",
        "2": "68",
        "4": "69",
        "player_id": "5390"
    },
    "44": {
        "Name": "Rod Curl",
        "Strokes": "279",
        "Purse": "1680",
        "Time (ET)": "-",
        "3": "68",
        "2": "69",
        "4": "69",
        "player_id": "361"
    },
    "45": {
        "Name": "Rex Caldwell",
        "Strokes": "279",
        "Purse": "1680",
        "Time (ET)": "-",
        "3": "73",
        "2": "70",
        "4": "69",
        "player_id": "479"
    },
    "46": {
        "Name": "Kermit Zarley",
        "Strokes": "278",
        "Purse": "2131",
        "Time (ET)": "-",
        "3": "68",
        "2": "67",
        "4": "69",
        "player_id": "798"
    },
    "47": {
        "Name": "Tom Weiskopf",
        "Strokes": "278",
        "Purse": "2131",
        "Time (ET)": "-",
        "3": "71",
        "2": "68",
        "4": "66",
        "player_id": "854"
    },
    "48": {
        "Name": "Lanny Wadkins",
        "Strokes": "278",
        "Purse": "2131",
        "Time (ET)": "-",
        "3": "72",
        "2": "68",
        "4": "69",
        "player_id": "161"
    },
    "49": {
        "Name": "Victor Regalado",
        "Strokes": "278",
        "Purse": "2131",
        "Time (ET)": "-",
        "3": "69",
        "2": "72",
        "4": "70",
        "player_id": "4947"
    },
    "50": {
        "Name": "Dana Quigley",
        "Strokes": "278",
        "Purse": "2131",
        "Time (ET)": "-",
        "3": "71",
        "2": "69",
        "4": "68",
        "player_id": "799"
    },
    "51": {
        "Name": "Lon Hinkle",
        "Strokes": "278",
        "Purse": "2131",
        "Time (ET)": "-",
        "3": "69",
        "2": "70",
        "4": "70",
        "player_id": "449"
    },
    "52": {
        "Name": "Dave Eichelberger",
        "Strokes": "278",
        "Purse": "2131",
        "Time (ET)": "-",
        "3": "71",
        "2": "69",
        "4": "67",
        "player_id": "778"
    },
    "53": {
        "Name": "Doug Campbell",
        "Strokes": "278",
        "Purse": "2131",
        "Time (ET)": "-",
        "3": "68",
        "2": "73",
        "4": "69",
        "player_id": "5495"
    },
    "54": {
        "Name": "Bobby Wadkins",
        "Strokes": "277",
        "Purse": "2905",
        "Time (ET)": "-",
        "3": "69",
        "2": "69",
        "4": "69",
        "player_id": "116"
    },
    "55": {
        "Name": "John Mahaffey",
        "Strokes": "277",
        "Purse": "2905",
        "Time (ET)": "-",
        "3": "72",
        "2": "70",
        "4": "69",
        "player_id": "121"
    },
    "56": {
        "Name": "Hale Irwin",
        "Strokes": "277",
        "Purse": "2905",
        "Time (ET)": "-",
        "3": "72",
        "2": "68",
        "4": "68",
        "player_id": "96"
    },
    "57": {
        "Name": "Ed Fiori",
        "Strokes": "277",
        "Purse": "2905",
        "Time (ET)": "-",
        "3": "69",
        "2": "70",
        "4": "67",
        "player_id": "150"
    },
    "58": {
        "Name": "Keith Fergus",
        "Strokes": "277",
        "Purse": "2905",
        "Time (ET)": "-",
        "3": "67",
        "2": "69",
        "4": "71",
        "player_id": "131"
    },
    "59": {
        "Name": "Sammy Rachels",
        "Strokes": "276",
        "Purse": "4242",
        "Time (ET)": "-",
        "3": "69",
        "2": "69",
        "4": "71",
        "player_id": "3954"
    },
    "60": {
        "Name": "Greg Powers",
        "Strokes": "276",
        "Purse": "4242",
        "Time (ET)": "-",
        "3": "70",
        "2": "68",
        "4": "71",
        "player_id": "470"
    },
    "61": {
        "Name": "Arnold Palmer",
        "Strokes": "276",
        "Purse": "4242",
        "Time (ET)": "-",
        "3": "72",
        "2": "69",
        "4": "64",
        "player_id": "224"
    },
    "62": {
        "Name": "Phil Hancock",
        "Strokes": "276",
        "Purse": "4242",
        "Time (ET)": "-",
        "3": "69",
        "2": "69",
        "4": "69",
        "player_id": "1286"
    },
    "63": {
        "Name": "Skip Dunaway",
        "Strokes": "276",
        "Purse": "4242",
        "Time (ET)": "-",
        "3": "72",
        "2": "67",
        "4": "71",
        "player_id": "5496"
    },
    "64": {
        "Name": "Mark Pfeil",
        "Strokes": "275",
        "Purse": "5425",
        "Time (ET)": "-",
        "3": "71",
        "2": "67",
        "4": "69",
        "player_id": "448"
    },
    "65": {
        "Name": "Jack Newton",
        "Strokes": "275",
        "Purse": "5425",
        "Time (ET)": "-",
        "3": "71",
        "2": "68",
        "4": "69",
        "player_id": "4996"
    },
    "66": {
        "Name": "Calvin Peete",
        "Strokes": "274",
        "Purse": "6860",
        "Time (ET)": "-",
        "3": "68",
        "2": "68",
        "4": "66",
        "player_id": "831"
    },
    "67": {
        "Name": "Dave Hill",
        "Strokes": "274",
        "Purse": "6860",
        "Time (ET)": "-",
        "3": "73",
        "2": "65",
        "4": "68",
        "player_id": "872"
    },
    "68": {
        "Name": "Jay Haas",
        "Strokes": "274",
        "Purse": "6860",
        "Time (ET)": "-",
        "3": "68",
        "2": "68",
        "4": "72",
        "player_id": "17"
    },
    "69": {
        "Name": "Lou Graham",
        "Strokes": "274",
        "Purse": "6860",
        "Time (ET)": "-",
        "3": "70",
        "2": "70",
        "4": "67",
        "player_id": "861"
    },
    "70": {
        "Name": "Andy Bean",
        "Strokes": "274",
        "Purse": "6860",
        "Time (ET)": "-",
        "3": "68",
        "2": "69",
        "4": "67",
        "player_id": "258"
    },
    "71": {
        "Name": "Barney Thompson",
        "Strokes": "273",
        "Purse": "9800",
        "Time (ET)": "-",
        "3": "70",
        "2": "67",
        "4": "67",
        "player_id": "1845"
    },
    "72": {
        "Name": "Ron Streck",
        "Strokes": "273",
        "Purse": "9800",
        "Time (ET)": "-",
        "3": "68",
        "2": "68",
        "4": "69",
        "player_id": "463"
    },
    "73": {
        "Name": "Jerry Pate",
        "Strokes": "273",
        "Purse": "9800",
        "Time (ET)": "-",
        "3": "66",
        "2": "66",
        "4": "69",
        "player_id": "675"
    },
    "74": {
        "Name": "George Burns",
        "Strokes": "273",
        "Purse": "9800",
        "Time (ET)": "-",
        "3": "70",
        "2": "67",
        "4": "68",
        "player_id": "420"
    },
    "75": {
        "Name": "Bill Rogers",
        "Strokes": "272",
        "Purse": "11725",
        "Time (ET)": "-",
        "3": "68",
        "2": "68",
        "4": "69",
        "player_id": "3605"
    },
    "76": {
        "Name": "D.A. Weibring",
        "Strokes": "270",
        "Purse": "13300",
        "Time (ET)": "-",
        "3": "66",
        "2": "68",
        "4": "68",
        "player_id": "37"
    },
    "77": {
        "Name": "Tom Kite",
        "Strokes": "270",
        "Purse": "13300",
        "Time (ET)": "-",
        "3": "65",
        "2": "69",
        "4": "66",
        "player_id": "105"
    },
    "78": {
        "Name": "Mike Reid",
        "Strokes": "268",
        "Purse": "20300",
        "Time (ET)": "-",
        "3": "69",
        "2": "64",
        "4": "66",
        "player_id": "140"
    },
    "79": {
        "Name": "Bob Gilder",
        "Strokes": "268",
        "Purse": "20300",
        "Time (ET)": "-",
        "3": "69",
        "2": "65",
        "4": "64",
        "player_id": "166"
    },
    "80": {
        "Name": "Lee Trevino",
        "Strokes": "266",
        "Purse": "37800",
        "Time (ET)": "-",
        "3": "68",
        "2": "66",
        "4": "65",
        "player_id": "784"
    },
    "81": {
        "Name": "Curtis Strange",
        "Strokes": "266",
        "Purse": "63000",
        "Time (ET)": "-",
        "3": "66",
        "2": "63",
        "4": "71",
        "player_id": "50"
    }
}